robin_logistics/Robin colored logo.png
robin_logistics/__init__.py
robin_logistics/cli.py
robin_logistics/dashboard.py
robin_logistics/environment.py
robin_logistics/headless.py
robin_logistics/solvers.py
robin_logistics/core/__init__.py
robin_logistics/core/config.py
robin_logistics/core/data_generator.py
robin_logistics/core/metrics/__init__.py
robin_logistics/core/metrics/calculator.py
robin_logistics/core/models/__init__.py
robin_logistics/core/models/node.py
robin_logistics/core/models/order.py
robin_logistics/core/models/sku.py
robin_logistics/core/models/vehicle.py
robin_logistics/core/models/warehouse.py
robin_logistics/core/network/__init__.py
robin_logistics/core/network/manager.py
robin_logistics/core/state/__init__.py
robin_logistics/core/state/orchestrator.py
robin_logistics/core/utils/__init__.py
robin_logistics/core/utils/distance.py
robin_logistics/core/validation/__init__.py
robin_logistics/core/validation/validator.py
robin_logistics/data/edges.csv
robin_logistics/data/network.pkl
robin_logistics/data/nodes.csv
robin_logistics_env-3.3.0.dist-info/licenses/LICENSE
robin_logistics_env-3.3.0.dist-info/METADATA
robin_logistics_env-3.3.0.dist-info/WHEEL
robin_logistics_env-3.3.0.dist-info/entry_points.txt
robin_logistics_env-3.3.0.dist-info/top_level.txt
robin_logistics_env-3.3.0.dist-info/RECORD
