Metadata-Version: 2.4
Name: robin-logistics-env
Version: 3.3.0
Summary: Professional multi-depot vehicle routing environment for hackathons and competitions with interactive dashboard and headless execution
Author-email: Robin <mario.salama@beltoneholding.com>
License: MIT
Project-URL: Homepage, https://github.com/RobinDataScience/Logistics-Env
Project-URL: Repository, https://github.com/RobinDataScience/Logistics-Env.git
Project-URL: Bug Tracker, https://github.com/RobinDataScience/Logistics-Env/issues
Keywords: logistics,optimization,vehicle-routing,hackathon,competition,simulation
Classifier: Development Status :: 5 - Production/Stable
Classifier: Intended Audience :: Education
Classifier: Intended Audience :: Developers
Classifier: License :: OSI Approved :: MIT License
Classifier: Operating System :: OS Independent
Classifier: Programming Language :: Python :: 3
Classifier: Programming Language :: Python :: 3.8
Classifier: Programming Language :: Python :: 3.9
Classifier: Programming Language :: Python :: 3.10
Classifier: Programming Language :: Python :: 3.11
Classifier: Programming Language :: Python :: 3.12
Classifier: Topic :: Scientific/Engineering :: Artificial Intelligence
Classifier: Topic :: Scientific/Engineering :: Mathematics
Classifier: Topic :: Software Development :: Libraries :: Python Modules
Classifier: Topic :: Education
Requires-Python: >=3.8
License-File: LICENSE
Requires-Dist: streamlit>=1.28.0
Requires-Dist: pandas>=1.5.0
Requires-Dist: numpy>=1.21.0
Requires-Dist: networkx>=2.8.0
Requires-Dist: folium>=0.14.0
Requires-Dist: streamlit-folium>=0.13.0
Requires-Dist: plotly>=5.0.0
Requires-Dist: scipy>=1.9.0
Dynamic: license-file
